dsa_package_AKV163/__init__.py
dsa_package_AKV163/dsa_sorting.py
dsa_package-0.0.1.dist-info/LICENSE
dsa_package-0.0.1.dist-info/METADATA
dsa_package-0.0.1.dist-info/WHEEL
dsa_package-0.0.1.dist-info/top_level.txt
dsa_package-0.0.1.dist-info/RECORD
